mempack/__init__.py
mempack/__main__.py
mempack/api.py
mempack/builder.py
mempack/chat.py
mempack/cli.py
mempack/config.py
mempack/errors.py
mempack/logging.py
mempack/retriever.py
mempack/types.py
mempack/embedding/__init__.py
mempack/embedding/base.py
mempack/embedding/external.py
mempack/embedding/sentence_tfm.py
mempack/index/__init__.py
mempack/index/ann_file.py
mempack/index/hnsw.py
mempack/pack/__init__.py
mempack/pack/reader.py
mempack/pack/spec.py
mempack/pack/toc.py
mempack/pack/writer.py
mempack/utils/__init__.py
mempack/utils/ecc.py
mempack/utils/hash.py
mempack/utils/io.py
mempack/utils/text.py
mempack/utils/time.py
mempack-0.1.0.dist-info/licenses/LICENSE
mempack-0.1.0.dist-info/METADATA
mempack-0.1.0.dist-info/WHEEL
mempack-0.1.0.dist-info/entry_points.txt
mempack-0.1.0.dist-info/top_level.txt
mempack-0.1.0.dist-info/RECORD
