Metadata-Version: 2.4
Name: mempack
Version: 0.1.0
Summary: A portable, fast knowledge pack with two-file ANN memory
Author: Mauro Canuto
License-Expression: Apache-2.0
Project-URL: Homepage, https://github.com/mempack/mempack
Project-URL: Repository, https://github.com/mempack/mempack
Project-URL: Documentation, https://mempack.readthedocs.io
Classifier: Development Status :: 3 - Alpha
Classifier: Intended Audience :: Developers
Classifier: Programming Language :: Python :: 3
Classifier: Programming Language :: Python :: 3.10
Classifier: Programming Language :: Python :: 3.11
Classifier: Programming Language :: Python :: 3.12
Requires-Python: >=3.10
License-File: LICENSE
Requires-Dist: numpy<2.0.0,>=1.24.0
Requires-Dist: pydantic>=2.10.0
Requires-Dist: tqdm>=4.66.0
Requires-Dist: zstandard>=0.23.0
Requires-Dist: xxhash>=3.5.0
Requires-Dist: cbor2>=5.6.0
Requires-Dist: sentence-transformers>=3.0.0
Requires-Dist: hnswlib>=0.8.0
Requires-Dist: typer>=0.12.0
Requires-Dist: rich>=13.8.0
Provides-Extra: dev
Requires-Dist: pytest>=8.0.0; extra == "dev"
Requires-Dist: pytest-cov>=5.0.0; extra == "dev"
Requires-Dist: ruff>=0.8.0; extra == "dev"
Requires-Dist: black>=24.0.0; extra == "dev"
Requires-Dist: isort>=5.13.0; extra == "dev"
Requires-Dist: mypy>=1.8.0; extra == "dev"
Requires-Dist: types-xxhash; extra == "dev"
Requires-Dist: types-requests; extra == "dev"
Provides-Extra: ecc
Requires-Dist: reedsolo>=1.7.0; extra == "ecc"
Provides-Extra: faiss
Requires-Dist: faiss-cpu>=1.7.0; extra == "faiss"
Dynamic: license-file
